VerilogHomework4/design.sv
module sequence_detector_11011(
    input clk, rst, din,
    output logic dout);

  enum logic [2:0] {
    S0 = 3'b000,
    S1 = 3'b001,
    S11 = 3'b010,
    S110 = 3'b011,
    S1101 = 3'b100,
    S11011 = 3'b101
  } state, state_next;

  always_ff @(posedge clk, posedge rst)
    if (rst) state <= S0;
    else state <= state_next;
  
  always_comb begin
	state_next = 'x;
    dout = '0;
    case(state)
      S0:
          if (din) state_next = S1;
          else state_next = S0;
      S1:
          if (din) state_next = S11;
          else state_next = S0;
      S11:
          if (~din) state_next = S110;
          else state_next = S11;
      S110:
          if (din) state_next = S1101;
          else state_next = S0;
      S1101:
          if (din) state_next = S11011;
          else state_next = S0;
      S11011:
        begin
          dout = '1;
          if (~din) state_next = S0;
          else state_next = S11;
        end
    endcase
  end
endmodule

VerilogHomework4/testbench.sv
`timescale 1us / 1ns

module sequence_detector_11011_test;
 
logic clk, din, dout, rst;

sequence_detector_11011 uut (.*);

localparam T = 10;
initial begin  
   clk = 0;
   forever #(T/2) clk = ~clk;
end

initial begin
   $dumpfile("dump.vcd");
   $dumpvars(1);
   din = 0;
   rst = 1;
   #T rst = 0;
   
   #(2*T);
   @(posedge clk) assert (dout == 1'b0) else $error("dout: expected=%b, actual=%b",1'b0,dout); 
    
   $display("Test 1");
   @(negedge clk) din = 1;
   @(posedge clk) assert (dout == 1'b0) else $error("dout: expected=%b, actual=%b",1'b0,dout); 
   @(posedge clk) assert (dout == 1'b0) else $error("dout: expected=%b, actual=%b",1'b0,dout);    
   @(negedge clk) din = 0;
   @(posedge clk) assert (dout == 1'b0) else $error("dout: expected=%b, actual=%b",1'b0,dout);    
   @(negedge clk) din = 1;
   @(posedge clk) assert (dout == 1'b0) else $error("dout: expected=%b, actual=%b",1'b0,dout);
   @(posedge clk) assert (dout == 1'b0) else $error("dout: expected=%b, actual=%b",1'b0,dout);        
   @(negedge clk) din = 0;
   @(posedge clk) assert (dout == 1'b1) else $error("dout: expected=%b, actual=%b",1'b1,dout);    
   @(posedge clk) assert (dout == 1'b0) else $error("dout: expected=%b, actual=%b",1'b0,dout);    
   
   $display("Test 2");   
   @(negedge clk) din = 1;
   @(posedge clk) assert (dout == 1'b0) else $error("dout: expected=%b, actual=%b",1'b0,dout); 
   @(posedge clk) assert (dout == 1'b0) else $error("dout: expected=%b, actual=%b",1'b0,dout);
   @(posedge clk) assert (dout == 1'b0) else $error("dout: expected=%b, actual=%b",1'b0,dout); 
   @(posedge clk) assert (dout == 1'b0) else $error("dout: expected=%b, actual=%b",1'b0,dout);           
   @(negedge clk) din = 0;
   @(posedge clk) assert (dout == 1'b0) else $error("dout: expected=%b, actual=%b",1'b0,dout);    
   @(negedge clk) din = 1;
   @(posedge clk) assert (dout == 1'b0) else $error("dout: expected=%b, actual=%b",1'b0,dout);
   @(posedge clk) assert (dout == 1'b0) else $error("dout: expected=%b, actual=%b",1'b0,dout);        
   @(negedge clk) din = 0;
   @(posedge clk) assert (dout == 1'b1) else $error("dout: expected=%b, actual=%b",1'b1,dout);    
   @(posedge clk) assert (dout == 1'b0) else $error("dout: expected=%b, actual=%b",1'b0,dout);    
 
   $display("Test 3");   
   @(negedge clk) din = 1;
   @(posedge clk) assert (dout == 1'b0) else $error("dout: expected=%b, actual=%b",1'b0,dout);           
   @(negedge clk) din = 0;
   @(posedge clk) assert (dout == 1'b0) else $error("dout: expected=%b, actual=%b",1'b0,dout);
   @(posedge clk) assert (dout == 1'b0) else $error("dout: expected=%b, actual=%b",1'b0,dout);        

   $display("Test 4");   
   @(negedge clk) din = 1;
   @(posedge clk) assert (dout == 1'b0) else $error("dout: expected=%b, actual=%b",1'b0,dout); 
   @(posedge clk) assert (dout == 1'b0) else $error("dout: expected=%b, actual=%b",1'b0,dout);         
   @(negedge clk) din = 0;
   @(posedge clk) assert (dout == 1'b0) else $error("dout: expected=%b, actual=%b",1'b0,dout);
   @(posedge clk) assert (dout == 1'b0) else $error("dout: expected=%b, actual=%b",1'b0,dout);        
   @(negedge clk) din = 1;
   @(posedge clk) assert (dout == 1'b0) else $error("dout: expected=%b, actual=%b",1'b0,dout);
   @(posedge clk) assert (dout == 1'b0) else $error("dout: expected=%b, actual=%b",1'b0,dout);        
   @(negedge clk) din = 0;
   @(posedge clk) assert (dout == 1'b0) else $error("dout: expected=%b, actual=%b",1'b0,dout);    
   @(negedge clk) din = 1;
   @(posedge clk) assert (dout == 1'b0) else $error("dout: expected=%b, actual=%b",1'b0,dout);
   @(posedge clk) assert (dout == 1'b0) else $error("dout: expected=%b, actual=%b",1'b0,dout); 
   @(posedge clk) assert (dout == 1'b1) else $error("dout: expected=%b, actual=%b",1'b1,dout);    
   @(posedge clk) assert (dout == 1'b0) else $error("dout: expected=%b, actual=%b",1'b0,dout);
   @(posedge clk) assert (dout == 1'b0) else $error("dout: expected=%b, actual=%b",1'b0,dout); 
   @(negedge clk) din = 0;
   @(posedge clk) assert (dout == 1'b0) else $error("dout: expected=%b, actual=%b",1'b0,dout);    
   @(negedge clk) din = 1;
   @(posedge clk) assert (dout == 1'b0) else $error("dout: expected=%b, actual=%b",1'b0,dout);
   @(posedge clk) assert (dout == 1'b0) else $error("dout: expected=%b, actual=%b",1'b0,dout); 
   @(posedge clk) assert (dout == 1'b1) else $error("dout: expected=%b, actual=%b",1'b1,dout); 
                       
   $finish; 
end

initial
    $display("din dout");
    
always @(posedge clk)
    $strobe(" %b    %b",din,dout);
    
endmodule

VerilogHomework4/dump.vcd
$date
	Sat Oct 21 15:13:18 2017
$end

$version
	Synopsys VCS version J-2014.12-SP1-1
$end

$timescale
	1ns
$end

$comment Csum: 1 f32cdabf342bb35b $end


$scope module sequence_detector_11011_test $end
$var reg 1 ! clk $end
$var reg 1 " din $end
$var reg 1 # dout $end
$var reg 1 $ rst $end
$upscope $end

$enddefinitions $end

#0
$dumpvars
0!
0"
0#
1$
$end
#5000
1!
#10000
0$
0!
#15000
1!
#20000
0!
#25000
1!
#30000
0!
#35000
1!
#40000
0!
1"
#45000
1!
#50000
0!
#55000
1!
#60000
0!
0"
#65000
1!
#70000
0!
1"
#75000
1!
#80000
0!
#85000
1!
1#
#90000
0!
0"
#95000
1!
0#
#100000
0!
#105000
1!
#110000
0!
1"
#115000
1!
#120000
0!
#125000
1!
#130000
0!
#135000
1!
#140000
0!
#145000
1!
#150000
0!
0"
#155000
1!
#160000
0!
1"
#165000
1!
#170000
0!
#175000
1!
1#
#180000
0!
0"
#185000
1!
0#
#190000
0!
#195000
1!
#200000
0!
1"
#205000
1!
#210000
0!
0"
#215000
1!
#220000
0!
#225000
1!
#230000
0!
1"
#235000
1!
#240000
0!
#245000
1!
#250000
0!
0"
#255000
1!
#260000
0!
#265000
1!
#270000
0!
1"
#275000
1!
#280000
0!
#285000
1!
#290000
0!
0"
#295000
1!
#300000
0!
1"
#305000
1!
#310000
0!
#315000
1!
1#
#320000
0!
#325000
1!
0#
#330000
0!
#335000
1!
#340000
0!
#345000
1!
#350000
0!
0"
#355000
1!
#360000
0!
1"
#365000
1!
#370000
0!
#375000
1!
1#
